{
  "_class": "symbolInstance",
  "booleanOperation": -1,
  "clippingMaskMode": 0,
  "do_objectID": "49BA6496-557E-49A7-BA36-E787ED4B4716",
  "exportOptions": {
    "_class": "exportOptions",
    "do_objectID": "C457A5AD-4896-4535-9616-AA86843AF9AB",
    "exportFormats": [
    ],
    "includedLayerIds": [
    ],
    "layerOptions": 0,
    "shouldTrim": false
  },
  "frame": {
    "_class": "rect",
    "constrainProportions": false,
    "do_objectID": "99C26732-B6D2-4FAA-B4A7-63F089B41F77",
    "height": 16,
    "width": 79,
    "x": 233,
    "y": 191
  },
  "hasClippingMask": false,
  "horizontalSpacing": 0,
  "isFixedToViewport": false,
  "isFlippedHorizontal": false,
  "isFlippedVertical": false,
  "isLocked": false,
  "isVisible": true,
  "layerListExpandedType": 0,
  "name": "Message__Status",
  "nameIsFixed": false,
  "overrideValues": [
    {
      "_class": "overrideValue",
      "do_objectID": "82AF7BD9-05DA-458A-8E08-C2034D16B164",
      "overrideName": "F88D4DD8-E919-40E6-8D66-FD03A01CCCBA_stringValue",
      "value": "Sending..."
    }
  ],
  "resizingConstraint": 63,
  "resizingType": 0,
  "rotation": 0,
  "scale": 1,
  "shouldBreakMaskChain": false,
  "style": {
    "_class": "style",
    "do_objectID": "8D93659C-8CA5-48B7-B472-B0B14ACAC028",
    "endMarkerType": 0,
    "miterLimit": 10,
    "startMarkerType": 0,
    "windingRule": 1
  },
  "symbolID": "881EBEFF-D245-490A-8BFC-F2B1ADE10A0D",
  "verticalSpacing": 0
}