{
  "_class": "group",
  "booleanOperation": 0,
  "clippingMaskMode": 0,
  "do_objectID": "BEDC5B2B-A953-4DF8-BD0C-5713EBA46BC1",
  "exportOptions": {
    "_class": "exportOptions",
    "do_objectID": "2B2C70FD-5806-4736-BFB8-4FA6399952CA",
    "exportFormats": [
    ],
    "includedLayerIds": [
    ],
    "layerOptions": 0,
    "shouldTrim": false
  },
  "frame": {
    "_class": "rect",
    "constrainProportions": false,
    "do_objectID": "12C96D4D-7C01-4EB6-8C47-47F42D2052CB",
    "height": 1024,
    "width": 508,
    "x": 0,
    "y": 0
  },
  "hasClickThrough": false,
  "hasClippingMask": false,
  "isFixedToViewport": false,
  "isFlippedHorizontal": false,
  "isFlippedVertical": false,
  "isLocked": false,
  "isVisible": true,
  "layerListExpandedType": 0,
  "layers": [
    {
      "class": "shapePath",
      "id": "8E32CACA-37F7-4912-A1BD-8A2CBDD7E233"
    },
    {
      "class": "group",
      "id": "C4EDC274-1D1D-4D29-915E-5740788CAFB4"
    },
    {
      "class": "group",
      "id": "91C48DEE-490E-41F6-A21B-776D3377AC9A"
    },
    {
      "class": "group",
      "id": "8E2AFFE3-A74A-49C0-9AD1-94C5564CEF32"
    },
    {
      "class": "group",
      "id": "93D5AB4F-4A0D-4BA2-B860-387D0C7B8D88"
    },
    {
      "class": "group",
      "id": "08C55511-96A6-462F-BB6D-858181C92A93"
    },
    {
      "class": "group",
      "id": "8C45A01E-EBC1-4CAA-9BDF-441C890CDAF6"
    },
    {
      "class": "group",
      "id": "E45EE1FD-208F-4411-868F-9979EA08E4F4"
    }
  ],
  "name": "phone",
  "nameIsFixed": true,
  "resizingConstraint": 63,
  "resizingType": 0,
  "rotation": 0,
  "shouldBreakMaskChain": false,
  "style": {
    "_class": "style",
    "blur": {
      "_class": "blur",
      "center": "{0.5, 0.5}",
      "do_objectID": "6B11C9AA-B293-4D54-98CD-7D93417CA368",
      "isEnabled": false,
      "motionAngle": 0,
      "radius": 12.018779342723,
      "saturation": 1,
      "type": 0
    },
    "do_objectID": "2AD3307B-7ED1-4498-80DB-B6D11DB6B9E0",
    "endMarkerType": 0,
    "miterLimit": 10,
    "startMarkerType": 0,
    "windingRule": 1
  }
}