{
  "_class": "group",
  "booleanOperation": -1,
  "clippingMaskMode": 0,
  "do_objectID": "F0C91EF6-CC69-41C3-AD05-A51CAA26966E",
  "exportOptions": {
    "_class": "exportOptions",
    "do_objectID": "C20CFB6E-8004-4C83-90FA-84F463062CB2",
    "exportFormats": [
    ],
    "includedLayerIds": [
    ],
    "layerOptions": 0,
    "shouldTrim": false
  },
  "frame": {
    "_class": "rect",
    "constrainProportions": false,
    "do_objectID": "12362887-FA42-42FC-B9AF-770409A787A5",
    "height": 416,
    "width": 1349.999999999996,
    "x": 2699.962746849517,
    "y": 0
  },
  "hasClickThrough": false,
  "hasClippingMask": false,
  "isFixedToViewport": false,
  "isFlippedHorizontal": false,
  "isFlippedVertical": false,
  "isLocked": false,
  "isVisible": true,
  "layerListExpandedType": 0,
  "layers": [
    {
      "class": "text",
      "id": "C559E978-96D2-44CF-9BD0-23D2E4F914A0"
    },
    {
      "class": "text",
      "id": "340DCCD9-157F-4153-B9FF-19BC1DF82952"
    },
    {
      "class": "text",
      "id": "0155B0AB-E83E-43C1-BD12-E355ED6CE6F0"
    },
    {
      "class": "text",
      "id": "3DDEAF86-9887-4382-8837-3718DEF33B21"
    },
    {
      "class": "text",
      "id": "84B0F3AD-D95F-4B52-A90A-80623501C817"
    },
    {
      "class": "text",
      "id": "28F2703F-BE3F-4112-8034-89E87CF888AD"
    },
    {
      "class": "text",
      "id": "17AF623B-07E4-4836-B081-5774BA5B1A1D"
    },
    {
      "class": "text",
      "id": "7D7075B9-1E24-48A8-A384-881E7669B322"
    },
    {
      "class": "text",
      "id": "E90231F4-D676-464F-83BB-D95440881B10"
    },
    {
      "class": "text",
      "id": "105DBD51-1350-4804-B56B-E21ADDB6561E"
    },
    {
      "class": "text",
      "id": "CE6A9B61-5CF3-4FDC-A3D8-8A5BBCC79B3B"
    },
    {
      "class": "text",
      "id": "9DB89AB5-7D80-4F8F-A4D0-EC8B062B9DE3"
    },
    {
      "class": "text",
      "id": "01589A5A-BFF5-448F-924D-2F853D45551D"
    },
    {
      "class": "text",
      "id": "54DC6775-E541-4CEC-8C48-80DF923CCA95"
    },
    {
      "class": "text",
      "id": "353B8562-E9D1-4BDC-827F-02098B7FCD46"
    },
    {
      "class": "text",
      "id": "2B5C4D24-EA28-4FFC-AEE6-285D3AE116F2"
    }
  ],
  "name": "Right",
  "nameIsFixed": true,
  "resizingConstraint": 63,
  "resizingType": 0,
  "rotation": 0,
  "shouldBreakMaskChain": false,
  "style": {
    "_class": "style",
    "do_objectID": "D6AC0478-4773-4E5B-99CD-2AABAD8B3124",
    "endMarkerType": 0,
    "miterLimit": 10,
    "startMarkerType": 0,
    "windingRule": 1
  },
  "userInfo": {
    "com.animaapp.stc-sketch-plugin": {
      "kModelPropertiesKey": {
      }
    }
  }
}