{
  "_class": "group",
  "booleanOperation": -1,
  "clippingMaskMode": 0,
  "do_objectID": "D95C9934-1CA6-444D-AB5C-0D69DEB9D1BC",
  "exportOptions": {
    "_class": "exportOptions",
    "do_objectID": "EACDA039-08C8-4A7B-ADCA-BE64F215FFB3",
    "exportFormats": [
    ],
    "includedLayerIds": [
    ],
    "layerOptions": 0,
    "shouldTrim": false
  },
  "frame": {
    "_class": "rect",
    "constrainProportions": false,
    "do_objectID": "C9F44616-6B78-421B-AAE1-9A35EBFD092D",
    "height": 32,
    "width": 100,
    "x": 0,
    "y": 108
  },
  "hasClickThrough": false,
  "hasClippingMask": false,
  "isFixedToViewport": false,
  "isFlippedHorizontal": false,
  "isFlippedVertical": false,
  "isLocked": false,
  "isVisible": true,
  "layerListExpandedType": 0,
  "layers": [
    {
      "class": "text",
      "id": "2B3515B5-5B6C-4994-833A-65CD328D87E9"
    },
    {
      "class": "text",
      "id": "DF230FA6-D108-4241-A103-78D8E41C7C03"
    }
  ],
  "name": "Text",
  "nameIsFixed": true,
  "resizingConstraint": 63,
  "resizingType": 0,
  "rotation": 0,
  "shouldBreakMaskChain": false,
  "style": {
    "_class": "style",
    "do_objectID": "81DE2CFF-4695-4144-9920-835C132B5DFB",
    "endMarkerType": 0,
    "miterLimit": 10,
    "startMarkerType": 0,
    "windingRule": 1
  },
  "userInfo": {
    "com.animaapp.stc-sketch-plugin": {
      "kModelPropertiesKey": {
      }
    }
  }
}