{
  "_class": "rectangle",
  "booleanOperation": -1,
  "clippingMaskMode": 0,
  "do_objectID": "0C2F6309-025D-43E4-848D-A6252B7A74F0",
  "edited": false,
  "exportOptions": {
    "_class": "exportOptions",
    "do_objectID": "DDEAA0B5-4AAE-4253-B89E-800C94D26FD0",
    "exportFormats": [
    ],
    "includedLayerIds": [
    ],
    "layerOptions": 0,
    "shouldTrim": false
  },
  "fixedRadius": 41.61005434782609,
  "frame": {
    "_class": "rect",
    "constrainProportions": false,
    "do_objectID": "9A792FB6-A84B-4E6C-B29C-965D4D1458F1",
    "height": 988,
    "width": 449.3885869565217,
    "x": 0,
    "y": 11
  },
  "hasClippingMask": false,
  "hasConvertedToNewRoundCorners": true,
  "isClosed": true,
  "isFixedToViewport": false,
  "isFlippedHorizontal": false,
  "isFlippedVertical": false,
  "isLocked": false,
  "isVisible": true,
  "layerListExpandedType": 1,
  "name": "Rectangle 9",
  "nameIsFixed": false,
  "pointRadiusBehaviour": 1,
  "points": [
    {
      "_class": "curvePoint",
      "cornerRadius": 41.61005434782609,
      "curveFrom": "{0, 0}",
      "curveMode": 1,
      "curveTo": "{0, 0}",
      "hasCurveFrom": false,
      "hasCurveTo": false,
      "point": "{0, 0}"
    },
    {
      "_class": "curvePoint",
      "cornerRadius": 41.61005434782609,
      "curveFrom": "{1, 0}",
      "curveMode": 1,
      "curveTo": "{1, 0}",
      "hasCurveFrom": false,
      "hasCurveTo": false,
      "point": "{1, 0}"
    },
    {
      "_class": "curvePoint",
      "cornerRadius": 41.61005434782609,
      "curveFrom": "{1, 0.99999999999999911}",
      "curveMode": 1,
      "curveTo": "{1, 0.99999999999999911}",
      "hasCurveFrom": false,
      "hasCurveTo": false,
      "point": "{1, 0.99999999999999911}"
    },
    {
      "_class": "curvePoint",
      "cornerRadius": 41.61005434782609,
      "curveFrom": "{0, 0.99999999999999911}",
      "curveMode": 1,
      "curveTo": "{0, 0.99999999999999911}",
      "hasCurveFrom": false,
      "hasCurveTo": false,
      "point": "{0, 0.99999999999999911}"
    }
  ],
  "resizingConstraint": 63,
  "resizingType": 0,
  "rotation": 0,
  "shouldBreakMaskChain": false,
  "style": {
    "_class": "style",
    "blur": {
      "_class": "blur",
      "center": "{0.5, 0.5}",
      "do_objectID": "3E6E3341-587D-42A5-B3B1-B2D56B20F384",
      "isEnabled": false,
      "motionAngle": 0,
      "radius": 8.322010869565217,
      "saturation": 1,
      "type": 0
    },
    "borders": [
      {
        "_class": "border",
        "color": {
          "_class": "color",
          "alpha": 1,
          "blue": 0.8721301020408163,
          "green": 0.8721301020408163,
          "red": 0.8721301020408163
        },
        "fillType": 0,
        "isEnabled": true,
        "position": 1,
        "thickness": 0.8322010869565217
      }
    ],
    "do_objectID": "0F79EF40-7D38-4985-BD16-D299A111EEB0",
    "endMarkerType": 0,
    "fills": [
      {
        "_class": "fill",
        "color": {
          "_class": "color",
          "alpha": 1,
          "blue": 0.9607843137254902,
          "green": 0.9529411764705882,
          "red": 0.9411764705882353
        },
        "fillType": 0,
        "isEnabled": true,
        "noiseIndex": 0,
        "noiseIntensity": 0,
        "patternFillType": 1,
        "patternTileScale": 1
      }
    ],
    "miterLimit": 10,
    "shadows": [
      {
        "_class": "shadow",
        "blurRadius": 41,
        "color": {
          "_class": "color",
          "alpha": 0.1206408514492754,
          "blue": 0,
          "green": 0,
          "red": 0
        },
        "contextSettings": {
          "_class": "graphicsContextSettings",
          "blendMode": 0,
          "opacity": 1
        },
        "isEnabled": true,
        "offsetX": 0,
        "offsetY": 0,
        "spread": 0
      }
    ],
    "startMarkerType": 0,
    "windingRule": 1
  }
}