{
  "_class": "group",
  "booleanOperation": -1,
  "clippingMaskMode": 0,
  "do_objectID": "E91C8278-9D1F-4945-A049-7853F89C8AB6",
  "exportOptions": {
    "_class": "exportOptions",
    "do_objectID": "7A4BD07E-FE74-488C-99C6-7F36DFBEEDFB",
    "exportFormats": [
    ],
    "includedLayerIds": [
    ],
    "layerOptions": 0,
    "shouldTrim": false
  },
  "frame": {
    "_class": "rect",
    "constrainProportions": false,
    "do_objectID": "C4A65A01-88C6-4F6F-9A0F-02D1A650CCD8",
    "height": 63,
    "width": 62,
    "x": 14,
    "y": 18
  },
  "hasClickThrough": false,
  "hasClippingMask": false,
  "isFixedToViewport": false,
  "isFlippedHorizontal": false,
  "isFlippedVertical": false,
  "isLocked": false,
  "isVisible": true,
  "layerListExpandedType": 0,
  "layers": [
    {
      "class": "text",
      "id": "2AE12304-F0E1-45C5-AF60-64B5C6F5A919"
    },
    {
      "class": "text",
      "id": "82AD6EDF-C7E1-4F88-BB51-A590F2AE267E"
    },
    {
      "class": "shapePath",
      "id": "FE43E44D-14E7-47BB-95C8-3799FE2DCD30"
    }
  ],
  "name": "added to order",
  "nameIsFixed": true,
  "resizingConstraint": 63,
  "resizingType": 0,
  "rotation": 0,
  "shouldBreakMaskChain": false,
  "style": {
    "_class": "style",
    "do_objectID": "86CAD960-5A70-42C9-A534-57B0C76AB0D9",
    "endMarkerType": 0,
    "miterLimit": 10,
    "startMarkerType": 0,
    "windingRule": 1
  }
}