{
  "_class": "group",
  "booleanOperation": -1,
  "clippingMaskMode": 0,
  "do_objectID": "F948EC62-D986-4283-AF0A-7B703182610E",
  "exportOptions": {
    "_class": "exportOptions",
    "do_objectID": "3BA02F85-B18C-4EBD-B311-E85E4F467392",
    "exportFormats": [
    ],
    "includedLayerIds": [
    ],
    "layerOptions": 0,
    "shouldTrim": false
  },
  "frame": {
    "_class": "rect",
    "constrainProportions": false,
    "do_objectID": "B66272B5-B14E-4661-83C1-048005BA99C5",
    "height": 100,
    "width": 417,
    "x": 0,
    "y": 30.92527173913038
  },
  "hasClickThrough": false,
  "hasClippingMask": false,
  "isFixedToViewport": false,
  "isFlippedHorizontal": false,
  "isFlippedVertical": false,
  "isLocked": false,
  "isVisible": true,
  "layerListExpandedType": 0,
  "layers": [
    {
      "class": "group",
      "id": "9E4C5F7A-5EE9-4E81-ADC4-B60071089451"
    },
    {
      "class": "group",
      "id": "B8442BA4-8CAA-4D9D-B8E3-17CE06CC6C2E"
    },
    {
      "class": "group",
      "id": "F2730688-9DD9-432A-A2EB-25E8BC7A2BD5"
    },
    {
      "class": "group",
      "id": "1D5BC8F0-9634-463E-A339-EA52979DB270"
    },
    {
      "class": "group",
      "id": "1096F039-099B-4216-9B33-9D5855ED5D58"
    }
  ],
  "name": "Flame grilled burger",
  "nameIsFixed": true,
  "resizingConstraint": 63,
  "resizingType": 0,
  "rotation": 0,
  "shouldBreakMaskChain": false,
  "style": {
    "_class": "style",
    "blur": {
      "_class": "blur",
      "center": "{0.5, 0.5}",
      "do_objectID": "3B04F610-2057-4C74-9CAC-11E6F8AE6613",
      "isEnabled": false,
      "motionAngle": 0,
      "radius": 8.322010869565217,
      "saturation": 1,
      "type": 0
    },
    "do_objectID": "B7516D81-1DE9-49C7-8A03-9C82E3E73340",
    "endMarkerType": 0,
    "miterLimit": 10,
    "startMarkerType": 0,
    "windingRule": 1
  }
}