{
  "_class": "shapePath",
  "booleanOperation": -1,
  "do_objectID": "67666295-0649-4956-9984-B29492BA6444",
  "edited": true,
  "exportOptions": {
    "_class": "exportOptions",
    "exportFormats": [
    ],
    "includedLayerIds": [
    ],
    "layerOptions": 0,
    "shouldTrim": false
  },
  "frame": {
    "_class": "rect",
    "constrainProportions": false,
    "height": 157.0000000000006,
    "width": 133,
    "x": 24.00000000000027,
    "y": 85.00000000000017
  },
  "isClosed": true,
  "isFixedToViewport": false,
  "isFlippedHorizontal": false,
  "isFlippedVertical": false,
  "isLocked": false,
  "isVisible": true,
  "layerListExpandedType": 0,
  "name": "Path",
  "nameIsFixed": false,
  "pointRadiusBehaviour": 1,
  "points": [
    {
      "_class": "curvePoint",
      "cornerRadius": 0,
      "curveFrom": "{1.2761423748999998, 1}",
      "curveMode": 1,
      "curveTo": "{0.83151021610309062, 1}",
      "hasCurveFrom": false,
      "hasCurveTo": false,
      "point": "{1, 1}"
    },
    {
      "_class": "curvePoint",
      "cornerRadius": 0,
      "curveFrom": "{0.99999999999999956, 0.18963735119936251}",
      "curveMode": 2,
      "curveTo": "{0.99999999999999956, 0.65749640676241794}",
      "hasCurveFrom": true,
      "hasCurveTo": true,
      "point": "{0.99999999999999956, 0.42356687898089024}"
    },
    {
      "_class": "curvePoint",
      "cornerRadius": 0,
      "curveFrom": "{0.22385762509999996, 0}",
      "curveMode": 2,
      "curveTo": "{0.77614237490000038, 0}",
      "hasCurveFrom": true,
      "hasCurveTo": true,
      "point": "{0.50000000000000044, 0}"
    },
    {
      "_class": "curvePoint",
      "cornerRadius": 0,
      "curveFrom": "{0, 0.51476302295166132}",
      "curveMode": 3,
      "curveTo": "{0, 0.18963735119936251}",
      "hasCurveFrom": true,
      "hasCurveTo": true,
      "point": "{0, 0.42356687898089024}"
    },
    {
      "_class": "curvePoint",
      "cornerRadius": 0,
      "curveFrom": "{0.094327291992068685, 1.1081842435678153}",
      "curveMode": 1,
      "curveTo": "{-0.054136613063179982, 0.930878217916697}",
      "hasCurveFrom": false,
      "hasCurveTo": false,
      "point": "{0.0037412264224195597, 0.99999999999999944}"
    }
  ],
  "resizingConstraint": 63,
  "resizingType": 0,
  "rotation": 0,
  "shouldBreakMaskChain": false
}