{
  "_class": "text",
  "attributedString": {
    "_class": "attributedString",
    "attributes": [
      {
        "_class": "stringAttribute",
        "attributes": {
          "MSAttributedStringColorAttribute": {
            "_class": "color",
            "alpha": 1,
            "blue": 0.7019607843137254,
            "green": 0.2627450980392157,
            "red": 0
          },
          "MSAttributedStringFontAttribute": {
            "_class": "fontDescriptor",
            "attributes": {
              "name": "Nunito-Regular",
              "size": 24
            }
          },
          "kerning": 0,
          "paragraphStyle": {
            "_class": "paragraphStyle",
            "alignment": 1,
            "maximumLineHeight": 28,
            "minimumLineHeight": 28
          },
          "textStyleVerticalAlignmentKey": 0
        },
        "length": 40,
        "location": 0
      }
    ],
    "string": "Nunito/24/Primary/Darken/4/Right/Regular"
  },
  "automaticallyDrawOnUnderlyingPath": false,
  "booleanOperation": -1,
  "clippingMaskMode": 0,
  "do_objectID": "B2F30963-F014-4FCD-A904-A2AE2DD56C84",
  "dontSynchroniseWithSymbol": false,
  "exportOptions": {
    "_class": "exportOptions",
    "do_objectID": "DF1A446C-25EF-4668-A9C1-51D6A76A9D18",
    "exportFormats": [
    ],
    "includedLayerIds": [
    ],
    "layerOptions": 0,
    "shouldTrim": false
  },
  "frame": {
    "_class": "rect",
    "constrainProportions": false,
    "do_objectID": "42412A97-3756-4C09-BB44-F24B5681232E",
    "height": 28,
    "width": 1349.981373424754,
    "x": 0,
    "y": 244
  },
  "glyphBounds": "{{894, 3}, {457, 24}}",
  "hasClippingMask": false,
  "isFixedToViewport": false,
  "isFlippedHorizontal": false,
  "isFlippedVertical": false,
  "isLocked": false,
  "isVisible": true,
  "layerListExpandedType": 0,
  "lineSpacingBehaviour": 2,
  "name": "Nunito/24/Primary/Darken/4/Right/Regular",
  "nameIsFixed": true,
  "resizingConstraint": 63,
  "resizingType": 0,
  "rotation": 0,
  "sharedStyleID": "70D33CD0-FCD2-44E5-8E91-7E79FC7B2C3A",
  "shouldBreakMaskChain": false,
  "style": {
    "_class": "style",
    "blur": {
      "_class": "blur",
      "center": "{0.5, 0.5}",
      "do_objectID": "6CC49A08-5C84-4538-822F-5B14A76257B6",
      "isEnabled": false,
      "motionAngle": 0,
      "radius": 8.322010869565217,
      "saturation": 1,
      "type": 0
    },
    "do_objectID": "A88FA36A-B9EA-4675-B179-39B85A392871",
    "endMarkerType": 0,
    "miterLimit": 10,
    "startMarkerType": 0,
    "textStyle": {
      "_class": "textStyle",
      "do_objectID": "DF338E8A-58C0-458D-9E48-E63C8542615F",
      "encodedAttributes": {
        "MSAttributedStringColorAttribute": {
          "_class": "color",
          "alpha": 1,
          "blue": 0.7019607843137254,
          "green": 0.2627450980392157,
          "red": 0
        },
        "MSAttributedStringFontAttribute": {
          "_class": "fontDescriptor",
          "attributes": {
            "name": "Nunito-Regular",
            "size": 24
          }
        },
        "kerning": 0,
        "paragraphStyle": {
          "_class": "paragraphStyle",
          "alignment": 1,
          "maximumLineHeight": 28,
          "minimumLineHeight": 28
        },
        "textStyleVerticalAlignmentKey": 0
      },
      "verticalAlignment": 0
    },
    "windingRule": 1
  },
  "textBehaviour": 1,
  "userInfo": {
    "com.animaapp.stc-sketch-plugin": {
      "kModelPropertiesKey": {
        "isAutoWidth": 0
      }
    }
  }
}