{
  "_class": "group",
  "booleanOperation": -1,
  "clippingMaskMode": 0,
  "do_objectID": "35E6305A-0511-4649-963A-F14E6C23D8A2",
  "exportOptions": {
    "_class": "exportOptions",
    "do_objectID": "68D925A3-F9A8-4947-A47D-F6D17A6E62B7",
    "exportFormats": [
    ],
    "includedLayerIds": [
    ],
    "layerOptions": 0,
    "shouldTrim": false
  },
  "frame": {
    "_class": "rect",
    "constrainProportions": false,
    "do_objectID": "6B5CEDB0-52F0-48AF-B2BB-15CC95121743",
    "height": 56,
    "width": 304,
    "x": 0,
    "y": 0
  },
  "hasClickThrough": false,
  "hasClippingMask": false,
  "isFixedToViewport": false,
  "isFlippedHorizontal": false,
  "isFlippedVertical": false,
  "isLocked": false,
  "isVisible": true,
  "layerListExpandedType": 0,
  "layers": [
    {
      "class": "symbolInstance",
      "id": "C8AE77A4-6BF5-42B6-A064-AD6B933EAD52"
    },
    {
      "class": "text",
      "id": "E3A2893E-7772-43A3-8363-4F2E846A1976"
    }
  ],
  "name": "__Bubble",
  "nameIsFixed": true,
  "resizingConstraint": 58,
  "resizingType": 0,
  "rotation": 0,
  "shouldBreakMaskChain": false,
  "style": {
    "_class": "style",
    "do_objectID": "F2FE1559-0B6B-4CE7-B654-067A9DD03B42",
    "endMarkerType": 0,
    "miterLimit": 10,
    "startMarkerType": 0,
    "windingRule": 1
  }
}