{
  "_class": "group",
  "booleanOperation": -1,
  "do_objectID": "FD686370-DA1E-44F6-8078-5C1A11F5E7D0",
  "exportOptions": {
    "_class": "exportOptions",
    "do_objectID": "6B79CC3D-181F-4D34-900E-E05A1E9E4077",
    "exportFormats": [
    ],
    "includedLayerIds": [
    ],
    "layerOptions": 0,
    "shouldTrim": false
  },
  "frame": {
    "_class": "rect",
    "constrainProportions": false,
    "do_objectID": "9CD810BE-5FE3-4974-A9AE-28E9DDF0F8AF",
    "height": 2308,
    "width": 1102,
    "x": 0,
    "y": 0
  },
  "hasClickThrough": false,
  "isFixedToViewport": false,
  "isFlippedHorizontal": false,
  "isFlippedVertical": false,
  "isLocked": false,
  "isVisible": true,
  "layerListExpandedType": 1,
  "layers": [
    {
      "class": "group",
      "id": "8DF9B8AC-17E0-4B4C-BB4A-C78BFD3F6993"
    },
    {
      "class": "group",
      "id": "D8BE3851-540E-4F8F-AE65-4903042D39FE"
    },
    {
      "class": "group",
      "id": "CEB4D472-CCD7-42B9-8975-442F2D8ABB9E"
    }
  ],
  "name": "iphone-mockup-1",
  "nameIsFixed": false,
  "resizingConstraint": 63,
  "resizingType": 0,
  "rotation": 0,
  "shouldBreakMaskChain": false,
  "style": {
    "_class": "style",
    "do_objectID": "A474B1BB-BE64-4AE6-8407-389EEAE9FC82",
    "endMarkerType": 0,
    "miterLimit": 10,
    "startMarkerType": 0,
    "windingRule": 1
  }
}