{
  "_class": "group",
  "booleanOperation": -1,
  "do_objectID": "F09B04EC-639F-43F9-BCF8-F84700E11C8B",
  "exportOptions": {
    "_class": "exportOptions",
    "do_objectID": "A517AA79-5098-447D-81B1-7C7CAF2C7E83",
    "exportFormats": [
    ],
    "includedLayerIds": [
    ],
    "layerOptions": 0,
    "shouldTrim": false
  },
  "frame": {
    "_class": "rect",
    "constrainProportions": false,
    "do_objectID": "05CDC9E7-5418-4C23-993D-AC9F719B546E",
    "height": 750,
    "width": 750,
    "x": 5679,
    "y": 1600
  },
  "hasClickThrough": false,
  "isFixedToViewport": false,
  "isFlippedHorizontal": false,
  "isFlippedVertical": false,
  "isLocked": false,
  "isVisible": true,
  "layerListExpandedType": 1,
  "layers": [
    {
      "class": "shapeGroup",
      "id": "51F2EF75-35CD-4A40-B4F9-D30242A51F40"
    },
    {
      "class": "group",
      "id": "6DC96EFA-F6B2-478F-9B31-0ED955D01EA0"
    }
  ],
  "name": "app icon",
  "nameIsFixed": true,
  "resizingConstraint": 63,
  "resizingType": 0,
  "rotation": 0,
  "shouldBreakMaskChain": false,
  "style": {
    "_class": "style",
    "do_objectID": "9CE25962-8DD9-4EF3-898B-4FEB6AD01808",
    "endMarkerType": 0,
    "miterLimit": 10,
    "startMarkerType": 0,
    "windingRule": 1
  }
}