{
  "_class": "symbolInstance",
  "booleanOperation": -1,
  "clippingMaskMode": 0,
  "do_objectID": "B66BF2C3-A4CC-47A3-A5C4-BE4573E00901",
  "exportOptions": {
    "_class": "exportOptions",
    "exportFormats": [
    ],
    "includedLayerIds": [
    ],
    "layerOptions": 0,
    "shouldTrim": false
  },
  "frame": {
    "_class": "rect",
    "constrainProportions": false,
    "height": 1024,
    "width": 357,
    "x": 158.177304964539,
    "y": 0.962441314553871
  },
  "hasClippingMask": false,
  "horizontalSpacing": 0,
  "isFixedToViewport": false,
  "isFlippedHorizontal": false,
  "isFlippedVertical": false,
  "isLocked": false,
  "isVisible": true,
  "layerListExpandedType": 0,
  "name": "container/border-radius/16",
  "nameIsFixed": false,
  "overrideValues": [
    {
      "_class": "overrideValue",
      "do_objectID": "190C7C2B-F09E-446A-A609-773D8D1D58E9",
      "overrideName": "F56FE067-F663-410A-931E-E12F4EA8CAFC_layerStyle",
      "value": "1C242335-215B-4AE4-93B9-F9CC7888F5AD"
    },
    {
      "_class": "overrideValue",
      "do_objectID": "F1B38B1C-66F5-4177-BEFF-679D857B3CC0",
      "overrideName": "A106937B-D865-470B-9ACF-ACD87C39D7D1_layerStyle",
      "value": "8C9C5AF1-BB7D-43C1-917D-5677AFDC67A8"
    }
  ],
  "resizingConstraint": 63,
  "resizingType": 0,
  "rotation": 0,
  "scale": 1,
  "shouldBreakMaskChain": false,
  "style": {
    "_class": "style",
    "endMarkerType": 0,
    "miterLimit": 10,
    "startMarkerType": 0,
    "windingRule": 1
  },
  "symbolID": "A2729F38-3FB6-4272-B4DA-3847E949B62E",
  "verticalSpacing": 0
}