{
  "_class": "group",
  "booleanOperation": -1,
  "clippingMaskMode": 0,
  "do_objectID": "3C135908-FA3A-4C9F-9638-926F35E1C457",
  "exportOptions": {
    "_class": "exportOptions",
    "do_objectID": "12430BFA-1F8D-40A0-A659-7F79EF2B02CF",
    "exportFormats": [
    ],
    "includedLayerIds": [
    ],
    "layerOptions": 0,
    "shouldTrim": false
  },
  "frame": {
    "_class": "rect",
    "constrainProportions": false,
    "do_objectID": "0A663CFD-A8E5-4BC6-BA91-1BF42D1F0BB8",
    "height": 416,
    "width": 1349.999999999996,
    "x": 2699.962746849517,
    "y": 0
  },
  "hasClickThrough": false,
  "hasClippingMask": false,
  "isFixedToViewport": false,
  "isFlippedHorizontal": false,
  "isFlippedVertical": false,
  "isLocked": false,
  "isVisible": true,
  "layerListExpandedType": 0,
  "layers": [
    {
      "class": "text",
      "id": "E7CFC778-A38F-4664-863F-150592105C40"
    },
    {
      "class": "text",
      "id": "D9917298-7B0C-4E02-952D-A1F51F239225"
    },
    {
      "class": "text",
      "id": "79FD25C4-2379-40E7-8CA3-3C8FB1FEEBE0"
    },
    {
      "class": "text",
      "id": "AD068915-D94D-4E25-BF02-82E082F973D5"
    },
    {
      "class": "text",
      "id": "2389B857-A64A-4079-958F-C8C47862E86A"
    },
    {
      "class": "text",
      "id": "82FAFF94-286F-45CB-B0D1-EF0292CAC034"
    },
    {
      "class": "text",
      "id": "BFD8E534-34EF-45A1-8054-763AE16B9CEA"
    },
    {
      "class": "text",
      "id": "87B45163-C4FE-4A9E-9207-DE4F0C29A79D"
    },
    {
      "class": "text",
      "id": "5B248651-7BF0-4365-9CD2-A5FEF8AD881B"
    },
    {
      "class": "text",
      "id": "E59173B4-F3CE-489E-ADF8-B200A5CA5E75"
    },
    {
      "class": "text",
      "id": "368A2BBD-CA42-4EEB-AAFE-FBA18254D212"
    },
    {
      "class": "text",
      "id": "E6DF2D56-4B04-4A21-B7C4-6483C0FD9628"
    },
    {
      "class": "text",
      "id": "C73D160B-BA38-4923-A77A-F2A6458F916A"
    },
    {
      "class": "text",
      "id": "AD675A72-FA7E-4D97-B256-25FF18071AF3"
    },
    {
      "class": "text",
      "id": "869265E6-5DCB-4C52-82EB-E497E785C7CA"
    },
    {
      "class": "text",
      "id": "56AD0F05-8AC7-4964-9EAB-FE8DFB5F0EA1"
    }
  ],
  "name": "Right",
  "nameIsFixed": true,
  "resizingConstraint": 63,
  "resizingType": 0,
  "rotation": 0,
  "shouldBreakMaskChain": false,
  "style": {
    "_class": "style",
    "do_objectID": "6201DB9F-0E8E-466A-86BC-F5E69CD68D39",
    "endMarkerType": 0,
    "miterLimit": 10,
    "startMarkerType": 0,
    "windingRule": 1
  },
  "userInfo": {
    "com.animaapp.stc-sketch-plugin": {
      "kModelPropertiesKey": {
      }
    }
  }
}