{
  "_class": "rectangle",
  "booleanOperation": -1,
  "clippingMaskMode": 0,
  "do_objectID": "A5D39A87-4E86-49DF-8CF1-B9EFBA0072FB",
  "edited": false,
  "exportOptions": {
    "_class": "exportOptions",
    "do_objectID": "07E15CAB-F2A8-469F-AE63-935D4D69DE8B",
    "exportFormats": [
    ],
    "includedLayerIds": [
    ],
    "layerOptions": 0,
    "shouldTrim": false
  },
  "fixedRadius": 2.403755868544601,
  "frame": {
    "_class": "rect",
    "constrainProportions": false,
    "do_objectID": "23F6A63B-06EC-4FC3-8567-57AF8D51ABBF",
    "height": 76.92018779342723,
    "width": 9.60756501182033,
    "x": 0,
    "y": 168.2629107981221
  },
  "hasClippingMask": false,
  "hasConvertedToNewRoundCorners": true,
  "isClosed": true,
  "isFixedToViewport": false,
  "isFlippedHorizontal": false,
  "isFlippedVertical": false,
  "isLocked": false,
  "isVisible": true,
  "layerListExpandedType": 0,
  "name": "vol-",
  "nameIsFixed": true,
  "pointRadiusBehaviour": 1,
  "points": [
    {
      "_class": "curvePoint",
      "cornerRadius": 2.403755868544601,
      "curveFrom": "{0, 0}",
      "curveMode": 1,
      "curveTo": "{0, 0}",
      "hasCurveFrom": false,
      "hasCurveTo": false,
      "point": "{0, 0}"
    },
    {
      "_class": "curvePoint",
      "cornerRadius": 2.403755868544601,
      "curveFrom": "{1.0000000000000002, 0}",
      "curveMode": 1,
      "curveTo": "{1.0000000000000002, 0}",
      "hasCurveFrom": false,
      "hasCurveTo": false,
      "point": "{1.0000000000000002, 0}"
    },
    {
      "_class": "curvePoint",
      "cornerRadius": 2.403755868544601,
      "curveFrom": "{1.0000000000000002, 0.99999999999999856}",
      "curveMode": 1,
      "curveTo": "{1.0000000000000002, 0.99999999999999856}",
      "hasCurveFrom": false,
      "hasCurveTo": false,
      "point": "{1.0000000000000002, 0.99999999999999856}"
    },
    {
      "_class": "curvePoint",
      "cornerRadius": 2.403755868544601,
      "curveFrom": "{0, 0.99999999999999856}",
      "curveMode": 1,
      "curveTo": "{0, 0.99999999999999856}",
      "hasCurveFrom": false,
      "hasCurveTo": false,
      "point": "{0, 0.99999999999999856}"
    }
  ],
  "resizingConstraint": 63,
  "resizingType": 0,
  "rotation": 0,
  "shouldBreakMaskChain": false,
  "style": {
    "_class": "style",
    "blur": {
      "_class": "blur",
      "center": "{0.5, 0.5}",
      "do_objectID": "FDAB9CB8-F35F-466D-8B47-B8A9C5AE4805",
      "isEnabled": false,
      "motionAngle": 0,
      "radius": 12.018779342723,
      "saturation": 1,
      "type": 0
    },
    "do_objectID": "390D389C-3316-4BF8-A53A-41B9DA3FBECE",
    "endMarkerType": 0,
    "fills": [
      {
        "_class": "fill",
        "color": {
          "_class": "color",
          "alpha": 1,
          "blue": 0,
          "green": 0,
          "red": 0
        },
        "fillType": 0,
        "isEnabled": true,
        "noiseIndex": 0,
        "noiseIntensity": 0,
        "patternFillType": 0,
        "patternTileScale": 1
      }
    ],
    "miterLimit": 10,
    "startMarkerType": 0,
    "windingRule": 1
  }
}