{
  "_class": "artboard",
  "backgroundColor": {
    "_class": "color",
    "alpha": 1,
    "blue": 0.9607843137254902,
    "do_objectID": "2491BC21-E41C-488D-B50A-F2C1E71E26AD",
    "green": 0.9529411764705882,
    "red": 0.9411764705882353
  },
  "booleanOperation": -1,
  "clippingMaskMode": 0,
  "do_objectID": "AFB4FEFD-F280-4787-B94F-16EE155953D3",
  "exportOptions": {
    "_class": "exportOptions",
    "do_objectID": "77F1B22C-3827-4F8D-B89E-AD8CD73ACCC4",
    "exportFormats": [
    ],
    "includedLayerIds": [
    ],
    "layerOptions": 0,
    "shouldTrim": false
  },
  "frame": {
    "_class": "rect",
    "constrainProportions": false,
    "do_objectID": "A67DD554-C747-4106-8CF6-C471ED8DE1F7",
    "height": 568,
    "width": 320,
    "x": 2654,
    "y": 3365
  },
  "hasBackgroundColor": true,
  "hasClickThrough": true,
  "hasClippingMask": false,
  "horizontalRulerData": {
    "_class": "rulerData",
    "base": 0,
    "do_objectID": "F4A4DC4E-B81D-4D4B-A8F2-6D4F99B8F992",
    "guides": [
    ]
  },
  "includeBackgroundColorInExport": true,
  "includeInCloudUpload": true,
  "isFixedToViewport": false,
  "isFlippedHorizontal": false,
  "isFlippedVertical": false,
  "isFlowHome": false,
  "isLocked": false,
  "isVisible": true,
  "layerListExpandedType": 1,
  "layers": [
    {
      "class": "group",
      "id": "DE6C5267-CA9C-4ADD-8623-B72304D47903"
    },
    {
      "class": "symbolInstance",
      "id": "61761FEF-7B51-451D-955D-94D72226BFAE"
    }
  ],
  "name": "Scenario B.09",
  "nameIsFixed": true,
  "presetDictionary": {
    "allowResizedMatching": 1,
    "height": 568,
    "name": "iPhone SE",
    "offersLandscapeVariant": 1,
    "width": 320
  },
  "resizesContent": false,
  "resizingConstraint": 63,
  "resizingType": 0,
  "rotation": 0,
  "shouldBreakMaskChain": true,
  "style": {
    "_class": "style",
    "do_objectID": "3D4B6337-8197-4B41-854E-A430839328EE",
    "endMarkerType": 0,
    "miterLimit": 10,
    "startMarkerType": 0,
    "windingRule": 1
  },
  "verticalRulerData": {
    "_class": "rulerData",
    "base": 0,
    "do_objectID": "4DBF78CB-B86B-4BC5-874F-CAEDC50047BC",
    "guides": [
    ]
  }
}