{
  "_class": "text",
  "attributedString": {
    "_class": "attributedString",
    "attributes": [
      {
        "_class": "stringAttribute",
        "attributes": {
          "MSAttributedStringColorAttribute": {
            "_class": "color",
            "alpha": 1,
            "blue": 0.5757599914965986,
            "green": 0.5757599914965986,
            "red": 0.5757599914965986
          },
          "MSAttributedStringFontAttribute": {
            "_class": "fontDescriptor",
            "attributes": {
              "name": "Nunito-SemiBold",
              "size": 11.6508152173913
            }
          },
          "kerning": 0,
          "paragraphStyle": {
            "_class": "paragraphStyle"
          },
          "textStyleVerticalAlignmentKey": 0
        },
        "length": 6,
        "location": 0
      }
    ],
    "string": "39 cal"
  },
  "automaticallyDrawOnUnderlyingPath": false,
  "booleanOperation": -1,
  "clippingMaskMode": 0,
  "do_objectID": "D91F12D6-EC42-4A13-8D2A-2FEE9E683285",
  "dontSynchroniseWithSymbol": false,
  "exportOptions": {
    "_class": "exportOptions",
    "do_objectID": "8D699C3D-EF8D-4CCD-B06D-F079A58FEA83",
    "exportFormats": [
    ],
    "includedLayerIds": [
    ],
    "layerOptions": 0,
    "shouldTrim": false
  },
  "frame": {
    "_class": "rect",
    "constrainProportions": false,
    "do_objectID": "446F3B7B-05C0-4842-AAA2-3E9C449C5577",
    "height": 16,
    "width": 40.8446824261883,
    "x": 9.522559049975305,
    "y": 2.001871186117458
  },
  "glyphBounds": "{{0, 3}, {31, 10}}",
  "hasClippingMask": false,
  "isFixedToViewport": false,
  "isFlippedHorizontal": false,
  "isFlippedVertical": false,
  "isLocked": false,
  "isVisible": true,
  "layerListExpandedType": 0,
  "lineSpacingBehaviour": 2,
  "name": "39 cal",
  "nameIsFixed": false,
  "resizingConstraint": 47,
  "resizingType": 0,
  "rotation": 0,
  "shouldBreakMaskChain": false,
  "style": {
    "_class": "style",
    "blur": {
      "_class": "blur",
      "center": "{0.5, 0.5}",
      "do_objectID": "A86551E0-B998-4C8D-84F3-FA0C965EFD65",
      "isEnabled": false,
      "motionAngle": 0,
      "radius": 8.322010869565217,
      "saturation": 1,
      "type": 0
    },
    "do_objectID": "D931EB9E-2083-4978-A746-1E1C8D5B7669",
    "endMarkerType": 0,
    "miterLimit": 10,
    "startMarkerType": 0,
    "textStyle": {
      "_class": "textStyle",
      "do_objectID": "A602404C-4934-4E83-9804-0344C5813E83",
      "encodedAttributes": {
        "MSAttributedStringColorAttribute": {
          "_class": "color",
          "alpha": 1,
          "blue": 0.5757599914965986,
          "green": 0.5757599914965986,
          "red": 0.5757599914965986
        },
        "MSAttributedStringFontAttribute": {
          "_class": "fontDescriptor",
          "attributes": {
            "name": "Nunito-SemiBold",
            "size": 11.6508152173913
          }
        },
        "kerning": 0,
        "paragraphStyle": {
          "_class": "paragraphStyle"
        },
        "textStyleVerticalAlignmentKey": 0
      },
      "verticalAlignment": 0
    },
    "windingRule": 1
  },
  "textBehaviour": 1
}