{
  "_class": "text",
  "attributedString": {
    "_class": "attributedString",
    "attributes": [
      {
        "_class": "stringAttribute",
        "attributes": {
          "MSAttributedStringColorAttribute": {
            "_class": "color",
            "alpha": 1,
            "blue": 0.4313725490196079,
            "green": 0.4313725490196079,
            "red": 0.4313725490196079
          },
          "MSAttributedStringFontAttribute": {
            "_class": "fontDescriptor",
            "attributes": {
              "name": "Nunito-Bold",
              "size": 19.97282608695652
            }
          },
          "kerning": 0,
          "paragraphStyle": {
            "_class": "paragraphStyle"
          },
          "textStyleVerticalAlignmentKey": 0
        },
        "length": 12,
        "location": 0
      }
    ],
    "string": "Crème brûlée"
  },
  "automaticallyDrawOnUnderlyingPath": false,
  "booleanOperation": -1,
  "clippingMaskMode": 0,
  "do_objectID": "07158959-4889-4C23-BF9C-9362177FE1D9",
  "dontSynchroniseWithSymbol": false,
  "exportOptions": {
    "_class": "exportOptions",
    "do_objectID": "16C134CA-5F19-454B-BCDE-BAAEC7317AF0",
    "exportFormats": [
    ],
    "includedLayerIds": [
    ],
    "layerOptions": 0,
    "shouldTrim": false
  },
  "frame": {
    "_class": "rect",
    "constrainProportions": false,
    "do_objectID": "AB77221F-9026-4554-91C7-274A6026508E",
    "height": 27,
    "width": 132,
    "x": 0,
    "y": 0.2803203661327121
  },
  "glyphBounds": "{{1, 4}, {122, 17}}",
  "hasClippingMask": false,
  "isFixedToViewport": false,
  "isFlippedHorizontal": false,
  "isFlippedVertical": false,
  "isLocked": false,
  "isVisible": true,
  "layerListExpandedType": 0,
  "lineSpacingBehaviour": 2,
  "name": "Crème brûlée",
  "nameIsFixed": false,
  "resizingConstraint": 47,
  "resizingType": 0,
  "rotation": 0,
  "shouldBreakMaskChain": false,
  "style": {
    "_class": "style",
    "blur": {
      "_class": "blur",
      "center": "{0.5, 0.5}",
      "do_objectID": "C4305C6D-1EBE-4F6E-AB89-15CCD9A9B08E",
      "isEnabled": false,
      "motionAngle": 0,
      "radius": 8.322010869565217,
      "saturation": 1,
      "type": 0
    },
    "do_objectID": "77B4FAB8-1834-409F-B847-67C975FA9DD5",
    "endMarkerType": 0,
    "miterLimit": 10,
    "startMarkerType": 0,
    "textStyle": {
      "_class": "textStyle",
      "do_objectID": "EEEFC678-1FA0-40C3-A59E-891E90294B33",
      "encodedAttributes": {
        "MSAttributedStringColorAttribute": {
          "_class": "color",
          "alpha": 1,
          "blue": 0.4313725490196079,
          "green": 0.4313725490196079,
          "red": 0.4313725490196079
        },
        "MSAttributedStringFontAttribute": {
          "_class": "fontDescriptor",
          "attributes": {
            "name": "Nunito-Bold",
            "size": 19.97282608695652
          }
        },
        "kerning": 0,
        "paragraphStyle": {
          "_class": "paragraphStyle"
        },
        "textStyleVerticalAlignmentKey": 0
      },
      "verticalAlignment": 0
    },
    "windingRule": 1
  },
  "textBehaviour": 1
}