{
  "_class": "group",
  "booleanOperation": -1,
  "do_objectID": "ABAB647C-CD84-4AE3-8DAD-796012A44ED0",
  "exportOptions": {
    "_class": "exportOptions",
    "exportFormats": [
    ],
    "includedLayerIds": [
    ],
    "layerOptions": 0,
    "shouldTrim": false
  },
  "frame": {
    "_class": "rect",
    "constrainProportions": false,
    "height": 1346,
    "width": 3775,
    "x": -864,
    "y": -193
  },
  "hasClickThrough": false,
  "isFixedToViewport": false,
  "isFlippedHorizontal": false,
  "isFlippedVertical": false,
  "isLocked": false,
  "isVisible": true,
  "layerListExpandedType": 0,
  "layers": [
    {
      "class": "shapeGroup",
      "id": "3363C3F9-DED4-4EB4-B08D-7C49FA607DA3"
    },
    {
      "class": "group",
      "id": "4805AACB-D916-4685-BA88-95E25280D2D3"
    },
    {
      "class": "group",
      "id": "D8DB243E-1930-4526-BACC-96211EE00325"
    }
  ],
  "name": "background",
  "nameIsFixed": true,
  "resizingConstraint": 63,
  "resizingType": 0,
  "rotation": 0,
  "shouldBreakMaskChain": false,
  "style": {
    "_class": "style",
    "endMarkerType": 0,
    "miterLimit": 10,
    "startMarkerType": 0,
    "windingRule": 1
  }
}