{
  "_class": "group",
  "booleanOperation": -1,
  "clippingMaskMode": 0,
  "do_objectID": "AC767730-212A-4C14-AE03-4858E1007C67",
  "exportOptions": {
    "_class": "exportOptions",
    "do_objectID": "61F340DA-3A5D-407D-95AA-22C2AFA76470",
    "exportFormats": [
    ],
    "includedLayerIds": [
    ],
    "layerOptions": 0,
    "shouldTrim": false
  },
  "frame": {
    "_class": "rect",
    "constrainProportions": false,
    "do_objectID": "D1A72F98-73C5-4B30-93FC-2E2C7D83A4BB",
    "height": 459,
    "width": 417,
    "x": 37,
    "y": 614
  },
  "hasClickThrough": false,
  "hasClippingMask": false,
  "isFixedToViewport": false,
  "isFlippedHorizontal": false,
  "isFlippedVertical": false,
  "isLocked": false,
  "isVisible": true,
  "layerListExpandedType": 2,
  "layers": [
    {
      "class": "group",
      "id": "5D7FE9F4-4F8C-459A-8B6A-EFA2A1CB2AE9"
    },
    {
      "class": "group",
      "id": "3C1889C2-5902-4723-BA53-3A10BE50465A"
    },
    {
      "class": "group",
      "id": "4F544379-5572-41EC-99D1-EDFE7FCC6098"
    },
    {
      "class": "group",
      "id": "5A41422D-5784-4025-9FC9-B1610495CDD4"
    },
    {
      "class": "text",
      "id": "72A9D0DA-AA11-4E15-A975-87B247B7CA2A"
    }
  ],
  "name": "Sweet treats",
  "nameIsFixed": true,
  "resizingConstraint": 63,
  "resizingType": 0,
  "rotation": 0,
  "shouldBreakMaskChain": false,
  "style": {
    "_class": "style",
    "blur": {
      "_class": "blur",
      "center": "{0.5, 0.5}",
      "do_objectID": "BAD877FB-4374-43CB-A560-775EFF0161D5",
      "isEnabled": false,
      "motionAngle": 0,
      "radius": 8.322010869565217,
      "saturation": 1,
      "type": 0
    },
    "do_objectID": "F1F72F80-0BAF-4248-9FDF-28248F46863C",
    "endMarkerType": 0,
    "miterLimit": 10,
    "startMarkerType": 0,
    "windingRule": 1
  }
}